{
  "kmer": 5,
  "vocab_size": 3125,
  "trained_vocab": {
    "-----": 0,
    "----A": 1,
    "----C": 2,
    "----G": 3,
    "----T": 4,
    "---A-": 5,
    "---AA": 6,
    "---AC": 7,
    "---AG": 8,
    "---AT": 9,
    "---C-": 10,
    "---CA": 11,
    "---CC": 12,
    "---CG": 13,
    "---CT": 14,
    "---G-": 15,
    "---GA": 16,
    "---GC": 17,
    "---GG": 18,
    "---GT": 19,
    "---T-": 20,
    "---TA": 21,
    "---TC": 22,
    "---TG": 23,
    "---TT": 24,
    "--A--": 25,
    "--A-A": 26,
    "--A-C": 27,
    "--A-G": 28,
    "--A-T": 29,
    "--AA-": 30,
    "--AAA": 31,
    "--AAC": 32,
    "--AAG": 33,
    "--AAT": 34,
    "--AC-": 35,
    "--ACA": 36,
    "--ACC": 37,
    "--ACG": 38,
    "--ACT": 39,
    "--AG-": 40,
    "--AGA": 41,
    "--AGC": 42,
    "--AGG": 43,
    "--AGT": 44,
    "--AT-": 45,
    "--ATA": 46,
    "--ATC": 47,
    "--ATG": 48,
    "--ATT": 49,
    "--C--": 50,
    "--C-A": 51,
    "--C-C": 52,
    "--C-G": 53,
    "--C-T": 54,
    "--CA-": 55,
    "--CAA": 56,
    "--CAC": 57,
    "--CAG": 58,
    "--CAT": 59,
    "--CC-": 60,
    "--CCA": 61,
    "--CCC": 62,
    "--CCG": 63,
    "--CCT": 64,
    "--CG-": 65,
    "--CGA": 66,
    "--CGC": 67,
    "--CGG": 68,
    "--CGT": 69,
    "--CT-": 70,
    "--CTA": 71,
    "--CTC": 72,
    "--CTG": 73,
    "--CTT": 74,
    "--G--": 75,
    "--G-A": 76,
    "--G-C": 77,
    "--G-G": 78,
    "--G-T": 79,
    "--GA-": 80,
    "--GAA": 81,
    "--GAC": 82,
    "--GAG": 83,
    "--GAT": 84,
    "--GC-": 85,
    "--GCA": 86,
    "--GCC": 87,
    "--GCG": 88,
    "--GCT": 89,
    "--GG-": 90,
    "--GGA": 91,
    "--GGC": 92,
    "--GGG": 93,
    "--GGT": 94,
    "--GT-": 95,
    "--GTA": 96,
    "--GTC": 97,
    "--GTG": 98,
    "--GTT": 99,
    "--T--": 100,
    "--T-A": 101,
    "--T-C": 102,
    "--T-G": 103,
    "--T-T": 104,
    "--TA-": 105,
    "--TAA": 106,
    "--TAC": 107,
    "--TAG": 108,
    "--TAT": 109,
    "--TC-": 110,
    "--TCA": 111,
    "--TCC": 112,
    "--TCG": 113,
    "--TCT": 114,
    "--TG-": 115,
    "--TGA": 116,
    "--TGC": 117,
    "--TGG": 118,
    "--TGT": 119,
    "--TT-": 120,
    "--TTA": 121,
    "--TTC": 122,
    "--TTG": 123,
    "--TTT": 124,
    "-A---": 125,
    "-A--A": 126,
    "-A--C": 127,
    "-A--G": 128,
    "-A--T": 129,
    "-A-A-": 130,
    "-A-AA": 131,
    "-A-AC": 132,
    "-A-AG": 133,
    "-A-AT": 134,
    "-A-C-": 135,
    "-A-CA": 136,
    "-A-CC": 137,
    "-A-CG": 138,
    "-A-CT": 139,
    "-A-G-": 140,
    "-A-GA": 141,
    "-A-GC": 142,
    "-A-GG": 143,
    "-A-GT": 144,
    "-A-T-": 145,
    "-A-TA": 146,
    "-A-TC": 147,
    "-A-TG": 148,
    "-A-TT": 149,
    "-AA--": 150,
    "-AA-A": 151,
    "-AA-C": 152,
    "-AA-G": 153,
    "-AA-T": 154,
    "-AAA-": 155,
    "-AAAA": 156,
    "-AAAC": 157,
    "-AAAG": 158,
    "-AAAT": 159,
    "-AAC-": 160,
    "-AACA": 161,
    "-AACC": 162,
    "-AACG": 163,
    "-AACT": 164,
    "-AAG-": 165,
    "-AAGA": 166,
    "-AAGC": 167,
    "-AAGG": 168,
    "-AAGT": 169,
    "-AAT-": 170,
    "-AATA": 171,
    "-AATC": 172,
    "-AATG": 173,
    "-AATT": 174,
    "-AC--": 175,
    "-AC-A": 176,
    "-AC-C": 177,
    "-AC-G": 178,
    "-AC-T": 179,
    "-ACA-": 180,
    "-ACAA": 181,
    "-ACAC": 182,
    "-ACAG": 183,
    "-ACAT": 184,
    "-ACC-": 185,
    "-ACCA": 186,
    "-ACCC": 187,
    "-ACCG": 188,
    "-ACCT": 189,
    "-ACG-": 190,
    "-ACGA": 191,
    "-ACGC": 192,
    "-ACGG": 193,
    "-ACGT": 194,
    "-ACT-": 195,
    "-ACTA": 196,
    "-ACTC": 197,
    "-ACTG": 198,
    "-ACTT": 199,
    "-AG--": 200,
    "-AG-A": 201,
    "-AG-C": 202,
    "-AG-G": 203,
    "-AG-T": 204,
    "-AGA-": 205,
    "-AGAA": 206,
    "-AGAC": 207,
    "-AGAG": 208,
    "-AGAT": 209,
    "-AGC-": 210,
    "-AGCA": 211,
    "-AGCC": 212,
    "-AGCG": 213,
    "-AGCT": 214,
    "-AGG-": 215,
    "-AGGA": 216,
    "-AGGC": 217,
    "-AGGG": 218,
    "-AGGT": 219,
    "-AGT-": 220,
    "-AGTA": 221,
    "-AGTC": 222,
    "-AGTG": 223,
    "-AGTT": 224,
    "-AT--": 225,
    "-AT-A": 226,
    "-AT-C": 227,
    "-AT-G": 228,
    "-AT-T": 229,
    "-ATA-": 230,
    "-ATAA": 231,
    "-ATAC": 232,
    "-ATAG": 233,
    "-ATAT": 234,
    "-ATC-": 235,
    "-ATCA": 236,
    "-ATCC": 237,
    "-ATCG": 238,
    "-ATCT": 239,
    "-ATG-": 240,
    "-ATGA": 241,
    "-ATGC": 242,
    "-ATGG": 243,
    "-ATGT": 244,
    "-ATT-": 245,
    "-ATTA": 246,
    "-ATTC": 247,
    "-ATTG": 248,
    "-ATTT": 249,
    "-C---": 250,
    "-C--A": 251,
    "-C--C": 252,
    "-C--G": 253,
    "-C--T": 254,
    "-C-A-": 255,
    "-C-AA": 256,
    "-C-AC": 257,
    "-C-AG": 258,
    "-C-AT": 259,
    "-C-C-": 260,
    "-C-CA": 261,
    "-C-CC": 262,
    "-C-CG": 263,
    "-C-CT": 264,
    "-C-G-": 265,
    "-C-GA": 266,
    "-C-GC": 267,
    "-C-GG": 268,
    "-C-GT": 269,
    "-C-T-": 270,
    "-C-TA": 271,
    "-C-TC": 272,
    "-C-TG": 273,
    "-C-TT": 274,
    "-CA--": 275,
    "-CA-A": 276,
    "-CA-C": 277,
    "-CA-G": 278,
    "-CA-T": 279,
    "-CAA-": 280,
    "-CAAA": 281,
    "-CAAC": 282,
    "-CAAG": 283,
    "-CAAT": 284,
    "-CAC-": 285,
    "-CACA": 286,
    "-CACC": 287,
    "-CACG": 288,
    "-CACT": 289,
    "-CAG-": 290,
    "-CAGA": 291,
    "-CAGC": 292,
    "-CAGG": 293,
    "-CAGT": 294,
    "-CAT-": 295,
    "-CATA": 296,
    "-CATC": 297,
    "-CATG": 298,
    "-CATT": 299,
    "-CC--": 300,
    "-CC-A": 301,
    "-CC-C": 302,
    "-CC-G": 303,
    "-CC-T": 304,
    "-CCA-": 305,
    "-CCAA": 306,
    "-CCAC": 307,
    "-CCAG": 308,
    "-CCAT": 309,
    "-CCC-": 310,
    "-CCCA": 311,
    "-CCCC": 312,
    "-CCCG": 313,
    "-CCCT": 314,
    "-CCG-": 315,
    "-CCGA": 316,
    "-CCGC": 317,
    "-CCGG": 318,
    "-CCGT": 319,
    "-CCT-": 320,
    "-CCTA": 321,
    "-CCTC": 322,
    "-CCTG": 323,
    "-CCTT": 324,
    "-CG--": 325,
    "-CG-A": 326,
    "-CG-C": 327,
    "-CG-G": 328,
    "-CG-T": 329,
    "-CGA-": 330,
    "-CGAA": 331,
    "-CGAC": 332,
    "-CGAG": 333,
    "-CGAT": 334,
    "-CGC-": 335,
    "-CGCA": 336,
    "-CGCC": 337,
    "-CGCG": 338,
    "-CGCT": 339,
    "-CGG-": 340,
    "-CGGA": 341,
    "-CGGC": 342,
    "-CGGG": 343,
    "-CGGT": 344,
    "-CGT-": 345,
    "-CGTA": 346,
    "-CGTC": 347,
    "-CGTG": 348,
    "-CGTT": 349,
    "-CT--": 350,
    "-CT-A": 351,
    "-CT-C": 352,
    "-CT-G": 353,
    "-CT-T": 354,
    "-CTA-": 355,
    "-CTAA": 356,
    "-CTAC": 357,
    "-CTAG": 358,
    "-CTAT": 359,
    "-CTC-": 360,
    "-CTCA": 361,
    "-CTCC": 362,
    "-CTCG": 363,
    "-CTCT": 364,
    "-CTG-": 365,
    "-CTGA": 366,
    "-CTGC": 367,
    "-CTGG": 368,
    "-CTGT": 369,
    "-CTT-": 370,
    "-CTTA": 371,
    "-CTTC": 372,
    "-CTTG": 373,
    "-CTTT": 374,
    "-G---": 375,
    "-G--A": 376,
    "-G--C": 377,
    "-G--G": 378,
    "-G--T": 379,
    "-G-A-": 380,
    "-G-AA": 381,
    "-G-AC": 382,
    "-G-AG": 383,
    "-G-AT": 384,
    "-G-C-": 385,
    "-G-CA": 386,
    "-G-CC": 387,
    "-G-CG": 388,
    "-G-CT": 389,
    "-G-G-": 390,
    "-G-GA": 391,
    "-G-GC": 392,
    "-G-GG": 393,
    "-G-GT": 394,
    "-G-T-": 395,
    "-G-TA": 396,
    "-G-TC": 397,
    "-G-TG": 398,
    "-G-TT": 399,
    "-GA--": 400,
    "-GA-A": 401,
    "-GA-C": 402,
    "-GA-G": 403,
    "-GA-T": 404,
    "-GAA-": 405,
    "-GAAA": 406,
    "-GAAC": 407,
    "-GAAG": 408,
    "-GAAT": 409,
    "-GAC-": 410,
    "-GACA": 411,
    "-GACC": 412,
    "-GACG": 413,
    "-GACT": 414,
    "-GAG-": 415,
    "-GAGA": 416,
    "-GAGC": 417,
    "-GAGG": 418,
    "-GAGT": 419,
    "-GAT-": 420,
    "-GATA": 421,
    "-GATC": 422,
    "-GATG": 423,
    "-GATT": 424,
    "-GC--": 425,
    "-GC-A": 426,
    "-GC-C": 427,
    "-GC-G": 428,
    "-GC-T": 429,
    "-GCA-": 430,
    "-GCAA": 431,
    "-GCAC": 432,
    "-GCAG": 433,
    "-GCAT": 434,
    "-GCC-": 435,
    "-GCCA": 436,
    "-GCCC": 437,
    "-GCCG": 438,
    "-GCCT": 439,
    "-GCG-": 440,
    "-GCGA": 441,
    "-GCGC": 442,
    "-GCGG": 443,
    "-GCGT": 444,
    "-GCT-": 445,
    "-GCTA": 446,
    "-GCTC": 447,
    "-GCTG": 448,
    "-GCTT": 449,
    "-GG--": 450,
    "-GG-A": 451,
    "-GG-C": 452,
    "-GG-G": 453,
    "-GG-T": 454,
    "-GGA-": 455,
    "-GGAA": 456,
    "-GGAC": 457,
    "-GGAG": 458,
    "-GGAT": 459,
    "-GGC-": 460,
    "-GGCA": 461,
    "-GGCC": 462,
    "-GGCG": 463,
    "-GGCT": 464,
    "-GGG-": 465,
    "-GGGA": 466,
    "-GGGC": 467,
    "-GGGG": 468,
    "-GGGT": 469,
    "-GGT-": 470,
    "-GGTA": 471,
    "-GGTC": 472,
    "-GGTG": 473,
    "-GGTT": 474,
    "-GT--": 475,
    "-GT-A": 476,
    "-GT-C": 477,
    "-GT-G": 478,
    "-GT-T": 479,
    "-GTA-": 480,
    "-GTAA": 481,
    "-GTAC": 482,
    "-GTAG": 483,
    "-GTAT": 484,
    "-GTC-": 485,
    "-GTCA": 486,
    "-GTCC": 487,
    "-GTCG": 488,
    "-GTCT": 489,
    "-GTG-": 490,
    "-GTGA": 491,
    "-GTGC": 492,
    "-GTGG": 493,
    "-GTGT": 494,
    "-GTT-": 495,
    "-GTTA": 496,
    "-GTTC": 497,
    "-GTTG": 498,
    "-GTTT": 499,
    "-T---": 500,
    "-T--A": 501,
    "-T--C": 502,
    "-T--G": 503,
    "-T--T": 504,
    "-T-A-": 505,
    "-T-AA": 506,
    "-T-AC": 507,
    "-T-AG": 508,
    "-T-AT": 509,
    "-T-C-": 510,
    "-T-CA": 511,
    "-T-CC": 512,
    "-T-CG": 513,
    "-T-CT": 514,
    "-T-G-": 515,
    "-T-GA": 516,
    "-T-GC": 517,
    "-T-GG": 518,
    "-T-GT": 519,
    "-T-T-": 520,
    "-T-TA": 521,
    "-T-TC": 522,
    "-T-TG": 523,
    "-T-TT": 524,
    "-TA--": 525,
    "-TA-A": 526,
    "-TA-C": 527,
    "-TA-G": 528,
    "-TA-T": 529,
    "-TAA-": 530,
    "-TAAA": 531,
    "-TAAC": 532,
    "-TAAG": 533,
    "-TAAT": 534,
    "-TAC-": 535,
    "-TACA": 536,
    "-TACC": 537,
    "-TACG": 538,
    "-TACT": 539,
    "-TAG-": 540,
    "-TAGA": 541,
    "-TAGC": 542,
    "-TAGG": 543,
    "-TAGT": 544,
    "-TAT-": 545,
    "-TATA": 546,
    "-TATC": 547,
    "-TATG": 548,
    "-TATT": 549,
    "-TC--": 550,
    "-TC-A": 551,
    "-TC-C": 552,
    "-TC-G": 553,
    "-TC-T": 554,
    "-TCA-": 555,
    "-TCAA": 556,
    "-TCAC": 557,
    "-TCAG": 558,
    "-TCAT": 559,
    "-TCC-": 560,
    "-TCCA": 561,
    "-TCCC": 562,
    "-TCCG": 563,
    "-TCCT": 564,
    "-TCG-": 565,
    "-TCGA": 566,
    "-TCGC": 567,
    "-TCGG": 568,
    "-TCGT": 569,
    "-TCT-": 570,
    "-TCTA": 571,
    "-TCTC": 572,
    "-TCTG": 573,
    "-TCTT": 574,
    "-TG--": 575,
    "-TG-A": 576,
    "-TG-C": 577,
    "-TG-G": 578,
    "-TG-T": 579,
    "-TGA-": 580,
    "-TGAA": 581,
    "-TGAC": 582,
    "-TGAG": 583,
    "-TGAT": 584,
    "-TGC-": 585,
    "-TGCA": 586,
    "-TGCC": 587,
    "-TGCG": 588,
    "-TGCT": 589,
    "-TGG-": 590,
    "-TGGA": 591,
    "-TGGC": 592,
    "-TGGG": 593,
    "-TGGT": 594,
    "-TGT-": 595,
    "-TGTA": 596,
    "-TGTC": 597,
    "-TGTG": 598,
    "-TGTT": 599,
    "-TT--": 600,
    "-TT-A": 601,
    "-TT-C": 602,
    "-TT-G": 603,
    "-TT-T": 604,
    "-TTA-": 605,
    "-TTAA": 606,
    "-TTAC": 607,
    "-TTAG": 608,
    "-TTAT": 609,
    "-TTC-": 610,
    "-TTCA": 611,
    "-TTCC": 612,
    "-TTCG": 613,
    "-TTCT": 614,
    "-TTG-": 615,
    "-TTGA": 616,
    "-TTGC": 617,
    "-TTGG": 618,
    "-TTGT": 619,
    "-TTT-": 620,
    "-TTTA": 621,
    "-TTTC": 622,
    "-TTTG": 623,
    "-TTTT": 624,
    "A----": 625,
    "A---A": 626,
    "A---C": 627,
    "A---G": 628,
    "A---T": 629,
    "A--A-": 630,
    "A--AA": 631,
    "A--AC": 632,
    "A--AG": 633,
    "A--AT": 634,
    "A--C-": 635,
    "A--CA": 636,
    "A--CC": 637,
    "A--CG": 638,
    "A--CT": 639,
    "A--G-": 640,
    "A--GA": 641,
    "A--GC": 642,
    "A--GG": 643,
    "A--GT": 644,
    "A--T-": 645,
    "A--TA": 646,
    "A--TC": 647,
    "A--TG": 648,
    "A--TT": 649,
    "A-A--": 650,
    "A-A-A": 651,
    "A-A-C": 652,
    "A-A-G": 653,
    "A-A-T": 654,
    "A-AA-": 655,
    "A-AAA": 656,
    "A-AAC": 657,
    "A-AAG": 658,
    "A-AAT": 659,
    "A-AC-": 660,
    "A-ACA": 661,
    "A-ACC": 662,
    "A-ACG": 663,
    "A-ACT": 664,
    "A-AG-": 665,
    "A-AGA": 666,
    "A-AGC": 667,
    "A-AGG": 668,
    "A-AGT": 669,
    "A-AT-": 670,
    "A-ATA": 671,
    "A-ATC": 672,
    "A-ATG": 673,
    "A-ATT": 674,
    "A-C--": 675,
    "A-C-A": 676,
    "A-C-C": 677,
    "A-C-G": 678,
    "A-C-T": 679,
    "A-CA-": 680,
    "A-CAA": 681,
    "A-CAC": 682,
    "A-CAG": 683,
    "A-CAT": 684,
    "A-CC-": 685,
    "A-CCA": 686,
    "A-CCC": 687,
    "A-CCG": 688,
    "A-CCT": 689,
    "A-CG-": 690,
    "A-CGA": 691,
    "A-CGC": 692,
    "A-CGG": 693,
    "A-CGT": 694,
    "A-CT-": 695,
    "A-CTA": 696,
    "A-CTC": 697,
    "A-CTG": 698,
    "A-CTT": 699,
    "A-G--": 700,
    "A-G-A": 701,
    "A-G-C": 702,
    "A-G-G": 703,
    "A-G-T": 704,
    "A-GA-": 705,
    "A-GAA": 706,
    "A-GAC": 707,
    "A-GAG": 708,
    "A-GAT": 709,
    "A-GC-": 710,
    "A-GCA": 711,
    "A-GCC": 712,
    "A-GCG": 713,
    "A-GCT": 714,
    "A-GG-": 715,
    "A-GGA": 716,
    "A-GGC": 717,
    "A-GGG": 718,
    "A-GGT": 719,
    "A-GT-": 720,
    "A-GTA": 721,
    "A-GTC": 722,
    "A-GTG": 723,
    "A-GTT": 724,
    "A-T--": 725,
    "A-T-A": 726,
    "A-T-C": 727,
    "A-T-G": 728,
    "A-T-T": 729,
    "A-TA-": 730,
    "A-TAA": 731,
    "A-TAC": 732,
    "A-TAG": 733,
    "A-TAT": 734,
    "A-TC-": 735,
    "A-TCA": 736,
    "A-TCC": 737,
    "A-TCG": 738,
    "A-TCT": 739,
    "A-TG-": 740,
    "A-TGA": 741,
    "A-TGC": 742,
    "A-TGG": 743,
    "A-TGT": 744,
    "A-TT-": 745,
    "A-TTA": 746,
    "A-TTC": 747,
    "A-TTG": 748,
    "A-TTT": 749,
    "AA---": 750,
    "AA--A": 751,
    "AA--C": 752,
    "AA--G": 753,
    "AA--T": 754,
    "AA-A-": 755,
    "AA-AA": 756,
    "AA-AC": 757,
    "AA-AG": 758,
    "AA-AT": 759,
    "AA-C-": 760,
    "AA-CA": 761,
    "AA-CC": 762,
    "AA-CG": 763,
    "AA-CT": 764,
    "AA-G-": 765,
    "AA-GA": 766,
    "AA-GC": 767,
    "AA-GG": 768,
    "AA-GT": 769,
    "AA-T-": 770,
    "AA-TA": 771,
    "AA-TC": 772,
    "AA-TG": 773,
    "AA-TT": 774,
    "AAA--": 775,
    "AAA-A": 776,
    "AAA-C": 777,
    "AAA-G": 778,
    "AAA-T": 779,
    "AAAA-": 780,
    "AAAAA": 781,
    "AAAAC": 782,
    "AAAAG": 783,
    "AAAAT": 784,
    "AAAC-": 785,
    "AAACA": 786,
    "AAACC": 787,
    "AAACG": 788,
    "AAACT": 789,
    "AAAG-": 790,
    "AAAGA": 791,
    "AAAGC": 792,
    "AAAGG": 793,
    "AAAGT": 794,
    "AAAT-": 795,
    "AAATA": 796,
    "AAATC": 797,
    "AAATG": 798,
    "AAATT": 799,
    "AAC--": 800,
    "AAC-A": 801,
    "AAC-C": 802,
    "AAC-G": 803,
    "AAC-T": 804,
    "AACA-": 805,
    "AACAA": 806,
    "AACAC": 807,
    "AACAG": 808,
    "AACAT": 809,
    "AACC-": 810,
    "AACCA": 811,
    "AACCC": 812,
    "AACCG": 813,
    "AACCT": 814,
    "AACG-": 815,
    "AACGA": 816,
    "AACGC": 817,
    "AACGG": 818,
    "AACGT": 819,
    "AACT-": 820,
    "AACTA": 821,
    "AACTC": 822,
    "AACTG": 823,
    "AACTT": 824,
    "AAG--": 825,
    "AAG-A": 826,
    "AAG-C": 827,
    "AAG-G": 828,
    "AAG-T": 829,
    "AAGA-": 830,
    "AAGAA": 831,
    "AAGAC": 832,
    "AAGAG": 833,
    "AAGAT": 834,
    "AAGC-": 835,
    "AAGCA": 836,
    "AAGCC": 837,
    "AAGCG": 838,
    "AAGCT": 839,
    "AAGG-": 840,
    "AAGGA": 841,
    "AAGGC": 842,
    "AAGGG": 843,
    "AAGGT": 844,
    "AAGT-": 845,
    "AAGTA": 846,
    "AAGTC": 847,
    "AAGTG": 848,
    "AAGTT": 849,
    "AAT--": 850,
    "AAT-A": 851,
    "AAT-C": 852,
    "AAT-G": 853,
    "AAT-T": 854,
    "AATA-": 855,
    "AATAA": 856,
    "AATAC": 857,
    "AATAG": 858,
    "AATAT": 859,
    "AATC-": 860,
    "AATCA": 861,
    "AATCC": 862,
    "AATCG": 863,
    "AATCT": 864,
    "AATG-": 865,
    "AATGA": 866,
    "AATGC": 867,
    "AATGG": 868,
    "AATGT": 869,
    "AATT-": 870,
    "AATTA": 871,
    "AATTC": 872,
    "AATTG": 873,
    "AATTT": 874,
    "AC---": 875,
    "AC--A": 876,
    "AC--C": 877,
    "AC--G": 878,
    "AC--T": 879,
    "AC-A-": 880,
    "AC-AA": 881,
    "AC-AC": 882,
    "AC-AG": 883,
    "AC-AT": 884,
    "AC-C-": 885,
    "AC-CA": 886,
    "AC-CC": 887,
    "AC-CG": 888,
    "AC-CT": 889,
    "AC-G-": 890,
    "AC-GA": 891,
    "AC-GC": 892,
    "AC-GG": 893,
    "AC-GT": 894,
    "AC-T-": 895,
    "AC-TA": 896,
    "AC-TC": 897,
    "AC-TG": 898,
    "AC-TT": 899,
    "ACA--": 900,
    "ACA-A": 901,
    "ACA-C": 902,
    "ACA-G": 903,
    "ACA-T": 904,
    "ACAA-": 905,
    "ACAAA": 906,
    "ACAAC": 907,
    "ACAAG": 908,
    "ACAAT": 909,
    "ACAC-": 910,
    "ACACA": 911,
    "ACACC": 912,
    "ACACG": 913,
    "ACACT": 914,
    "ACAG-": 915,
    "ACAGA": 916,
    "ACAGC": 917,
    "ACAGG": 918,
    "ACAGT": 919,
    "ACAT-": 920,
    "ACATA": 921,
    "ACATC": 922,
    "ACATG": 923,
    "ACATT": 924,
    "ACC--": 925,
    "ACC-A": 926,
    "ACC-C": 927,
    "ACC-G": 928,
    "ACC-T": 929,
    "ACCA-": 930,
    "ACCAA": 931,
    "ACCAC": 932,
    "ACCAG": 933,
    "ACCAT": 934,
    "ACCC-": 935,
    "ACCCA": 936,
    "ACCCC": 937,
    "ACCCG": 938,
    "ACCCT": 939,
    "ACCG-": 940,
    "ACCGA": 941,
    "ACCGC": 942,
    "ACCGG": 943,
    "ACCGT": 944,
    "ACCT-": 945,
    "ACCTA": 946,
    "ACCTC": 947,
    "ACCTG": 948,
    "ACCTT": 949,
    "ACG--": 950,
    "ACG-A": 951,
    "ACG-C": 952,
    "ACG-G": 953,
    "ACG-T": 954,
    "ACGA-": 955,
    "ACGAA": 956,
    "ACGAC": 957,
    "ACGAG": 958,
    "ACGAT": 959,
    "ACGC-": 960,
    "ACGCA": 961,
    "ACGCC": 962,
    "ACGCG": 963,
    "ACGCT": 964,
    "ACGG-": 965,
    "ACGGA": 966,
    "ACGGC": 967,
    "ACGGG": 968,
    "ACGGT": 969,
    "ACGT-": 970,
    "ACGTA": 971,
    "ACGTC": 972,
    "ACGTG": 973,
    "ACGTT": 974,
    "ACT--": 975,
    "ACT-A": 976,
    "ACT-C": 977,
    "ACT-G": 978,
    "ACT-T": 979,
    "ACTA-": 980,
    "ACTAA": 981,
    "ACTAC": 982,
    "ACTAG": 983,
    "ACTAT": 984,
    "ACTC-": 985,
    "ACTCA": 986,
    "ACTCC": 987,
    "ACTCG": 988,
    "ACTCT": 989,
    "ACTG-": 990,
    "ACTGA": 991,
    "ACTGC": 992,
    "ACTGG": 993,
    "ACTGT": 994,
    "ACTT-": 995,
    "ACTTA": 996,
    "ACTTC": 997,
    "ACTTG": 998,
    "ACTTT": 999,
    "AG---": 1000,
    "AG--A": 1001,
    "AG--C": 1002,
    "AG--G": 1003,
    "AG--T": 1004,
    "AG-A-": 1005,
    "AG-AA": 1006,
    "AG-AC": 1007,
    "AG-AG": 1008,
    "AG-AT": 1009,
    "AG-C-": 1010,
    "AG-CA": 1011,
    "AG-CC": 1012,
    "AG-CG": 1013,
    "AG-CT": 1014,
    "AG-G-": 1015,
    "AG-GA": 1016,
    "AG-GC": 1017,
    "AG-GG": 1018,
    "AG-GT": 1019,
    "AG-T-": 1020,
    "AG-TA": 1021,
    "AG-TC": 1022,
    "AG-TG": 1023,
    "AG-TT": 1024,
    "AGA--": 1025,
    "AGA-A": 1026,
    "AGA-C": 1027,
    "AGA-G": 1028,
    "AGA-T": 1029,
    "AGAA-": 1030,
    "AGAAA": 1031,
    "AGAAC": 1032,
    "AGAAG": 1033,
    "AGAAT": 1034,
    "AGAC-": 1035,
    "AGACA": 1036,
    "AGACC": 1037,
    "AGACG": 1038,
    "AGACT": 1039,
    "AGAG-": 1040,
    "AGAGA": 1041,
    "AGAGC": 1042,
    "AGAGG": 1043,
    "AGAGT": 1044,
    "AGAT-": 1045,
    "AGATA": 1046,
    "AGATC": 1047,
    "AGATG": 1048,
    "AGATT": 1049,
    "AGC--": 1050,
    "AGC-A": 1051,
    "AGC-C": 1052,
    "AGC-G": 1053,
    "AGC-T": 1054,
    "AGCA-": 1055,
    "AGCAA": 1056,
    "AGCAC": 1057,
    "AGCAG": 1058,
    "AGCAT": 1059,
    "AGCC-": 1060,
    "AGCCA": 1061,
    "AGCCC": 1062,
    "AGCCG": 1063,
    "AGCCT": 1064,
    "AGCG-": 1065,
    "AGCGA": 1066,
    "AGCGC": 1067,
    "AGCGG": 1068,
    "AGCGT": 1069,
    "AGCT-": 1070,
    "AGCTA": 1071,
    "AGCTC": 1072,
    "AGCTG": 1073,
    "AGCTT": 1074,
    "AGG--": 1075,
    "AGG-A": 1076,
    "AGG-C": 1077,
    "AGG-G": 1078,
    "AGG-T": 1079,
    "AGGA-": 1080,
    "AGGAA": 1081,
    "AGGAC": 1082,
    "AGGAG": 1083,
    "AGGAT": 1084,
    "AGGC-": 1085,
    "AGGCA": 1086,
    "AGGCC": 1087,
    "AGGCG": 1088,
    "AGGCT": 1089,
    "AGGG-": 1090,
    "AGGGA": 1091,
    "AGGGC": 1092,
    "AGGGG": 1093,
    "AGGGT": 1094,
    "AGGT-": 1095,
    "AGGTA": 1096,
    "AGGTC": 1097,
    "AGGTG": 1098,
    "AGGTT": 1099,
    "AGT--": 1100,
    "AGT-A": 1101,
    "AGT-C": 1102,
    "AGT-G": 1103,
    "AGT-T": 1104,
    "AGTA-": 1105,
    "AGTAA": 1106,
    "AGTAC": 1107,
    "AGTAG": 1108,
    "AGTAT": 1109,
    "AGTC-": 1110,
    "AGTCA": 1111,
    "AGTCC": 1112,
    "AGTCG": 1113,
    "AGTCT": 1114,
    "AGTG-": 1115,
    "AGTGA": 1116,
    "AGTGC": 1117,
    "AGTGG": 1118,
    "AGTGT": 1119,
    "AGTT-": 1120,
    "AGTTA": 1121,
    "AGTTC": 1122,
    "AGTTG": 1123,
    "AGTTT": 1124,
    "AT---": 1125,
    "AT--A": 1126,
    "AT--C": 1127,
    "AT--G": 1128,
    "AT--T": 1129,
    "AT-A-": 1130,
    "AT-AA": 1131,
    "AT-AC": 1132,
    "AT-AG": 1133,
    "AT-AT": 1134,
    "AT-C-": 1135,
    "AT-CA": 1136,
    "AT-CC": 1137,
    "AT-CG": 1138,
    "AT-CT": 1139,
    "AT-G-": 1140,
    "AT-GA": 1141,
    "AT-GC": 1142,
    "AT-GG": 1143,
    "AT-GT": 1144,
    "AT-T-": 1145,
    "AT-TA": 1146,
    "AT-TC": 1147,
    "AT-TG": 1148,
    "AT-TT": 1149,
    "ATA--": 1150,
    "ATA-A": 1151,
    "ATA-C": 1152,
    "ATA-G": 1153,
    "ATA-T": 1154,
    "ATAA-": 1155,
    "ATAAA": 1156,
    "ATAAC": 1157,
    "ATAAG": 1158,
    "ATAAT": 1159,
    "ATAC-": 1160,
    "ATACA": 1161,
    "ATACC": 1162,
    "ATACG": 1163,
    "ATACT": 1164,
    "ATAG-": 1165,
    "ATAGA": 1166,
    "ATAGC": 1167,
    "ATAGG": 1168,
    "ATAGT": 1169,
    "ATAT-": 1170,
    "ATATA": 1171,
    "ATATC": 1172,
    "ATATG": 1173,
    "ATATT": 1174,
    "ATC--": 1175,
    "ATC-A": 1176,
    "ATC-C": 1177,
    "ATC-G": 1178,
    "ATC-T": 1179,
    "ATCA-": 1180,
    "ATCAA": 1181,
    "ATCAC": 1182,
    "ATCAG": 1183,
    "ATCAT": 1184,
    "ATCC-": 1185,
    "ATCCA": 1186,
    "ATCCC": 1187,
    "ATCCG": 1188,
    "ATCCT": 1189,
    "ATCG-": 1190,
    "ATCGA": 1191,
    "ATCGC": 1192,
    "ATCGG": 1193,
    "ATCGT": 1194,
    "ATCT-": 1195,
    "ATCTA": 1196,
    "ATCTC": 1197,
    "ATCTG": 1198,
    "ATCTT": 1199,
    "ATG--": 1200,
    "ATG-A": 1201,
    "ATG-C": 1202,
    "ATG-G": 1203,
    "ATG-T": 1204,
    "ATGA-": 1205,
    "ATGAA": 1206,
    "ATGAC": 1207,
    "ATGAG": 1208,
    "ATGAT": 1209,
    "ATGC-": 1210,
    "ATGCA": 1211,
    "ATGCC": 1212,
    "ATGCG": 1213,
    "ATGCT": 1214,
    "ATGG-": 1215,
    "ATGGA": 1216,
    "ATGGC": 1217,
    "ATGGG": 1218,
    "ATGGT": 1219,
    "ATGT-": 1220,
    "ATGTA": 1221,
    "ATGTC": 1222,
    "ATGTG": 1223,
    "ATGTT": 1224,
    "ATT--": 1225,
    "ATT-A": 1226,
    "ATT-C": 1227,
    "ATT-G": 1228,
    "ATT-T": 1229,
    "ATTA-": 1230,
    "ATTAA": 1231,
    "ATTAC": 1232,
    "ATTAG": 1233,
    "ATTAT": 1234,
    "ATTC-": 1235,
    "ATTCA": 1236,
    "ATTCC": 1237,
    "ATTCG": 1238,
    "ATTCT": 1239,
    "ATTG-": 1240,
    "ATTGA": 1241,
    "ATTGC": 1242,
    "ATTGG": 1243,
    "ATTGT": 1244,
    "ATTT-": 1245,
    "ATTTA": 1246,
    "ATTTC": 1247,
    "ATTTG": 1248,
    "ATTTT": 1249,
    "C----": 1250,
    "C---A": 1251,
    "C---C": 1252,
    "C---G": 1253,
    "C---T": 1254,
    "C--A-": 1255,
    "C--AA": 1256,
    "C--AC": 1257,
    "C--AG": 1258,
    "C--AT": 1259,
    "C--C-": 1260,
    "C--CA": 1261,
    "C--CC": 1262,
    "C--CG": 1263,
    "C--CT": 1264,
    "C--G-": 1265,
    "C--GA": 1266,
    "C--GC": 1267,
    "C--GG": 1268,
    "C--GT": 1269,
    "C--T-": 1270,
    "C--TA": 1271,
    "C--TC": 1272,
    "C--TG": 1273,
    "C--TT": 1274,
    "C-A--": 1275,
    "C-A-A": 1276,
    "C-A-C": 1277,
    "C-A-G": 1278,
    "C-A-T": 1279,
    "C-AA-": 1280,
    "C-AAA": 1281,
    "C-AAC": 1282,
    "C-AAG": 1283,
    "C-AAT": 1284,
    "C-AC-": 1285,
    "C-ACA": 1286,
    "C-ACC": 1287,
    "C-ACG": 1288,
    "C-ACT": 1289,
    "C-AG-": 1290,
    "C-AGA": 1291,
    "C-AGC": 1292,
    "C-AGG": 1293,
    "C-AGT": 1294,
    "C-AT-": 1295,
    "C-ATA": 1296,
    "C-ATC": 1297,
    "C-ATG": 1298,
    "C-ATT": 1299,
    "C-C--": 1300,
    "C-C-A": 1301,
    "C-C-C": 1302,
    "C-C-G": 1303,
    "C-C-T": 1304,
    "C-CA-": 1305,
    "C-CAA": 1306,
    "C-CAC": 1307,
    "C-CAG": 1308,
    "C-CAT": 1309,
    "C-CC-": 1310,
    "C-CCA": 1311,
    "C-CCC": 1312,
    "C-CCG": 1313,
    "C-CCT": 1314,
    "C-CG-": 1315,
    "C-CGA": 1316,
    "C-CGC": 1317,
    "C-CGG": 1318,
    "C-CGT": 1319,
    "C-CT-": 1320,
    "C-CTA": 1321,
    "C-CTC": 1322,
    "C-CTG": 1323,
    "C-CTT": 1324,
    "C-G--": 1325,
    "C-G-A": 1326,
    "C-G-C": 1327,
    "C-G-G": 1328,
    "C-G-T": 1329,
    "C-GA-": 1330,
    "C-GAA": 1331,
    "C-GAC": 1332,
    "C-GAG": 1333,
    "C-GAT": 1334,
    "C-GC-": 1335,
    "C-GCA": 1336,
    "C-GCC": 1337,
    "C-GCG": 1338,
    "C-GCT": 1339,
    "C-GG-": 1340,
    "C-GGA": 1341,
    "C-GGC": 1342,
    "C-GGG": 1343,
    "C-GGT": 1344,
    "C-GT-": 1345,
    "C-GTA": 1346,
    "C-GTC": 1347,
    "C-GTG": 1348,
    "C-GTT": 1349,
    "C-T--": 1350,
    "C-T-A": 1351,
    "C-T-C": 1352,
    "C-T-G": 1353,
    "C-T-T": 1354,
    "C-TA-": 1355,
    "C-TAA": 1356,
    "C-TAC": 1357,
    "C-TAG": 1358,
    "C-TAT": 1359,
    "C-TC-": 1360,
    "C-TCA": 1361,
    "C-TCC": 1362,
    "C-TCG": 1363,
    "C-TCT": 1364,
    "C-TG-": 1365,
    "C-TGA": 1366,
    "C-TGC": 1367,
    "C-TGG": 1368,
    "C-TGT": 1369,
    "C-TT-": 1370,
    "C-TTA": 1371,
    "C-TTC": 1372,
    "C-TTG": 1373,
    "C-TTT": 1374,
    "CA---": 1375,
    "CA--A": 1376,
    "CA--C": 1377,
    "CA--G": 1378,
    "CA--T": 1379,
    "CA-A-": 1380,
    "CA-AA": 1381,
    "CA-AC": 1382,
    "CA-AG": 1383,
    "CA-AT": 1384,
    "CA-C-": 1385,
    "CA-CA": 1386,
    "CA-CC": 1387,
    "CA-CG": 1388,
    "CA-CT": 1389,
    "CA-G-": 1390,
    "CA-GA": 1391,
    "CA-GC": 1392,
    "CA-GG": 1393,
    "CA-GT": 1394,
    "CA-T-": 1395,
    "CA-TA": 1396,
    "CA-TC": 1397,
    "CA-TG": 1398,
    "CA-TT": 1399,
    "CAA--": 1400,
    "CAA-A": 1401,
    "CAA-C": 1402,
    "CAA-G": 1403,
    "CAA-T": 1404,
    "CAAA-": 1405,
    "CAAAA": 1406,
    "CAAAC": 1407,
    "CAAAG": 1408,
    "CAAAT": 1409,
    "CAAC-": 1410,
    "CAACA": 1411,
    "CAACC": 1412,
    "CAACG": 1413,
    "CAACT": 1414,
    "CAAG-": 1415,
    "CAAGA": 1416,
    "CAAGC": 1417,
    "CAAGG": 1418,
    "CAAGT": 1419,
    "CAAT-": 1420,
    "CAATA": 1421,
    "CAATC": 1422,
    "CAATG": 1423,
    "CAATT": 1424,
    "CAC--": 1425,
    "CAC-A": 1426,
    "CAC-C": 1427,
    "CAC-G": 1428,
    "CAC-T": 1429,
    "CACA-": 1430,
    "CACAA": 1431,
    "CACAC": 1432,
    "CACAG": 1433,
    "CACAT": 1434,
    "CACC-": 1435,
    "CACCA": 1436,
    "CACCC": 1437,
    "CACCG": 1438,
    "CACCT": 1439,
    "CACG-": 1440,
    "CACGA": 1441,
    "CACGC": 1442,
    "CACGG": 1443,
    "CACGT": 1444,
    "CACT-": 1445,
    "CACTA": 1446,
    "CACTC": 1447,
    "CACTG": 1448,
    "CACTT": 1449,
    "CAG--": 1450,
    "CAG-A": 1451,
    "CAG-C": 1452,
    "CAG-G": 1453,
    "CAG-T": 1454,
    "CAGA-": 1455,
    "CAGAA": 1456,
    "CAGAC": 1457,
    "CAGAG": 1458,
    "CAGAT": 1459,
    "CAGC-": 1460,
    "CAGCA": 1461,
    "CAGCC": 1462,
    "CAGCG": 1463,
    "CAGCT": 1464,
    "CAGG-": 1465,
    "CAGGA": 1466,
    "CAGGC": 1467,
    "CAGGG": 1468,
    "CAGGT": 1469,
    "CAGT-": 1470,
    "CAGTA": 1471,
    "CAGTC": 1472,
    "CAGTG": 1473,
    "CAGTT": 1474,
    "CAT--": 1475,
    "CAT-A": 1476,
    "CAT-C": 1477,
    "CAT-G": 1478,
    "CAT-T": 1479,
    "CATA-": 1480,
    "CATAA": 1481,
    "CATAC": 1482,
    "CATAG": 1483,
    "CATAT": 1484,
    "CATC-": 1485,
    "CATCA": 1486,
    "CATCC": 1487,
    "CATCG": 1488,
    "CATCT": 1489,
    "CATG-": 1490,
    "CATGA": 1491,
    "CATGC": 1492,
    "CATGG": 1493,
    "CATGT": 1494,
    "CATT-": 1495,
    "CATTA": 1496,
    "CATTC": 1497,
    "CATTG": 1498,
    "CATTT": 1499,
    "CC---": 1500,
    "CC--A": 1501,
    "CC--C": 1502,
    "CC--G": 1503,
    "CC--T": 1504,
    "CC-A-": 1505,
    "CC-AA": 1506,
    "CC-AC": 1507,
    "CC-AG": 1508,
    "CC-AT": 1509,
    "CC-C-": 1510,
    "CC-CA": 1511,
    "CC-CC": 1512,
    "CC-CG": 1513,
    "CC-CT": 1514,
    "CC-G-": 1515,
    "CC-GA": 1516,
    "CC-GC": 1517,
    "CC-GG": 1518,
    "CC-GT": 1519,
    "CC-T-": 1520,
    "CC-TA": 1521,
    "CC-TC": 1522,
    "CC-TG": 1523,
    "CC-TT": 1524,
    "CCA--": 1525,
    "CCA-A": 1526,
    "CCA-C": 1527,
    "CCA-G": 1528,
    "CCA-T": 1529,
    "CCAA-": 1530,
    "CCAAA": 1531,
    "CCAAC": 1532,
    "CCAAG": 1533,
    "CCAAT": 1534,
    "CCAC-": 1535,
    "CCACA": 1536,
    "CCACC": 1537,
    "CCACG": 1538,
    "CCACT": 1539,
    "CCAG-": 1540,
    "CCAGA": 1541,
    "CCAGC": 1542,
    "CCAGG": 1543,
    "CCAGT": 1544,
    "CCAT-": 1545,
    "CCATA": 1546,
    "CCATC": 1547,
    "CCATG": 1548,
    "CCATT": 1549,
    "CCC--": 1550,
    "CCC-A": 1551,
    "CCC-C": 1552,
    "CCC-G": 1553,
    "CCC-T": 1554,
    "CCCA-": 1555,
    "CCCAA": 1556,
    "CCCAC": 1557,
    "CCCAG": 1558,
    "CCCAT": 1559,
    "CCCC-": 1560,
    "CCCCA": 1561,
    "CCCCC": 1562,
    "CCCCG": 1563,
    "CCCCT": 1564,
    "CCCG-": 1565,
    "CCCGA": 1566,
    "CCCGC": 1567,
    "CCCGG": 1568,
    "CCCGT": 1569,
    "CCCT-": 1570,
    "CCCTA": 1571,
    "CCCTC": 1572,
    "CCCTG": 1573,
    "CCCTT": 1574,
    "CCG--": 1575,
    "CCG-A": 1576,
    "CCG-C": 1577,
    "CCG-G": 1578,
    "CCG-T": 1579,
    "CCGA-": 1580,
    "CCGAA": 1581,
    "CCGAC": 1582,
    "CCGAG": 1583,
    "CCGAT": 1584,
    "CCGC-": 1585,
    "CCGCA": 1586,
    "CCGCC": 1587,
    "CCGCG": 1588,
    "CCGCT": 1589,
    "CCGG-": 1590,
    "CCGGA": 1591,
    "CCGGC": 1592,
    "CCGGG": 1593,
    "CCGGT": 1594,
    "CCGT-": 1595,
    "CCGTA": 1596,
    "CCGTC": 1597,
    "CCGTG": 1598,
    "CCGTT": 1599,
    "CCT--": 1600,
    "CCT-A": 1601,
    "CCT-C": 1602,
    "CCT-G": 1603,
    "CCT-T": 1604,
    "CCTA-": 1605,
    "CCTAA": 1606,
    "CCTAC": 1607,
    "CCTAG": 1608,
    "CCTAT": 1609,
    "CCTC-": 1610,
    "CCTCA": 1611,
    "CCTCC": 1612,
    "CCTCG": 1613,
    "CCTCT": 1614,
    "CCTG-": 1615,
    "CCTGA": 1616,
    "CCTGC": 1617,
    "CCTGG": 1618,
    "CCTGT": 1619,
    "CCTT-": 1620,
    "CCTTA": 1621,
    "CCTTC": 1622,
    "CCTTG": 1623,
    "CCTTT": 1624,
    "CG---": 1625,
    "CG--A": 1626,
    "CG--C": 1627,
    "CG--G": 1628,
    "CG--T": 1629,
    "CG-A-": 1630,
    "CG-AA": 1631,
    "CG-AC": 1632,
    "CG-AG": 1633,
    "CG-AT": 1634,
    "CG-C-": 1635,
    "CG-CA": 1636,
    "CG-CC": 1637,
    "CG-CG": 1638,
    "CG-CT": 1639,
    "CG-G-": 1640,
    "CG-GA": 1641,
    "CG-GC": 1642,
    "CG-GG": 1643,
    "CG-GT": 1644,
    "CG-T-": 1645,
    "CG-TA": 1646,
    "CG-TC": 1647,
    "CG-TG": 1648,
    "CG-TT": 1649,
    "CGA--": 1650,
    "CGA-A": 1651,
    "CGA-C": 1652,
    "CGA-G": 1653,
    "CGA-T": 1654,
    "CGAA-": 1655,
    "CGAAA": 1656,
    "CGAAC": 1657,
    "CGAAG": 1658,
    "CGAAT": 1659,
    "CGAC-": 1660,
    "CGACA": 1661,
    "CGACC": 1662,
    "CGACG": 1663,
    "CGACT": 1664,
    "CGAG-": 1665,
    "CGAGA": 1666,
    "CGAGC": 1667,
    "CGAGG": 1668,
    "CGAGT": 1669,
    "CGAT-": 1670,
    "CGATA": 1671,
    "CGATC": 1672,
    "CGATG": 1673,
    "CGATT": 1674,
    "CGC--": 1675,
    "CGC-A": 1676,
    "CGC-C": 1677,
    "CGC-G": 1678,
    "CGC-T": 1679,
    "CGCA-": 1680,
    "CGCAA": 1681,
    "CGCAC": 1682,
    "CGCAG": 1683,
    "CGCAT": 1684,
    "CGCC-": 1685,
    "CGCCA": 1686,
    "CGCCC": 1687,
    "CGCCG": 1688,
    "CGCCT": 1689,
    "CGCG-": 1690,
    "CGCGA": 1691,
    "CGCGC": 1692,
    "CGCGG": 1693,
    "CGCGT": 1694,
    "CGCT-": 1695,
    "CGCTA": 1696,
    "CGCTC": 1697,
    "CGCTG": 1698,
    "CGCTT": 1699,
    "CGG--": 1700,
    "CGG-A": 1701,
    "CGG-C": 1702,
    "CGG-G": 1703,
    "CGG-T": 1704,
    "CGGA-": 1705,
    "CGGAA": 1706,
    "CGGAC": 1707,
    "CGGAG": 1708,
    "CGGAT": 1709,
    "CGGC-": 1710,
    "CGGCA": 1711,
    "CGGCC": 1712,
    "CGGCG": 1713,
    "CGGCT": 1714,
    "CGGG-": 1715,
    "CGGGA": 1716,
    "CGGGC": 1717,
    "CGGGG": 1718,
    "CGGGT": 1719,
    "CGGT-": 1720,
    "CGGTA": 1721,
    "CGGTC": 1722,
    "CGGTG": 1723,
    "CGGTT": 1724,
    "CGT--": 1725,
    "CGT-A": 1726,
    "CGT-C": 1727,
    "CGT-G": 1728,
    "CGT-T": 1729,
    "CGTA-": 1730,
    "CGTAA": 1731,
    "CGTAC": 1732,
    "CGTAG": 1733,
    "CGTAT": 1734,
    "CGTC-": 1735,
    "CGTCA": 1736,
    "CGTCC": 1737,
    "CGTCG": 1738,
    "CGTCT": 1739,
    "CGTG-": 1740,
    "CGTGA": 1741,
    "CGTGC": 1742,
    "CGTGG": 1743,
    "CGTGT": 1744,
    "CGTT-": 1745,
    "CGTTA": 1746,
    "CGTTC": 1747,
    "CGTTG": 1748,
    "CGTTT": 1749,
    "CT---": 1750,
    "CT--A": 1751,
    "CT--C": 1752,
    "CT--G": 1753,
    "CT--T": 1754,
    "CT-A-": 1755,
    "CT-AA": 1756,
    "CT-AC": 1757,
    "CT-AG": 1758,
    "CT-AT": 1759,
    "CT-C-": 1760,
    "CT-CA": 1761,
    "CT-CC": 1762,
    "CT-CG": 1763,
    "CT-CT": 1764,
    "CT-G-": 1765,
    "CT-GA": 1766,
    "CT-GC": 1767,
    "CT-GG": 1768,
    "CT-GT": 1769,
    "CT-T-": 1770,
    "CT-TA": 1771,
    "CT-TC": 1772,
    "CT-TG": 1773,
    "CT-TT": 1774,
    "CTA--": 1775,
    "CTA-A": 1776,
    "CTA-C": 1777,
    "CTA-G": 1778,
    "CTA-T": 1779,
    "CTAA-": 1780,
    "CTAAA": 1781,
    "CTAAC": 1782,
    "CTAAG": 1783,
    "CTAAT": 1784,
    "CTAC-": 1785,
    "CTACA": 1786,
    "CTACC": 1787,
    "CTACG": 1788,
    "CTACT": 1789,
    "CTAG-": 1790,
    "CTAGA": 1791,
    "CTAGC": 1792,
    "CTAGG": 1793,
    "CTAGT": 1794,
    "CTAT-": 1795,
    "CTATA": 1796,
    "CTATC": 1797,
    "CTATG": 1798,
    "CTATT": 1799,
    "CTC--": 1800,
    "CTC-A": 1801,
    "CTC-C": 1802,
    "CTC-G": 1803,
    "CTC-T": 1804,
    "CTCA-": 1805,
    "CTCAA": 1806,
    "CTCAC": 1807,
    "CTCAG": 1808,
    "CTCAT": 1809,
    "CTCC-": 1810,
    "CTCCA": 1811,
    "CTCCC": 1812,
    "CTCCG": 1813,
    "CTCCT": 1814,
    "CTCG-": 1815,
    "CTCGA": 1816,
    "CTCGC": 1817,
    "CTCGG": 1818,
    "CTCGT": 1819,
    "CTCT-": 1820,
    "CTCTA": 1821,
    "CTCTC": 1822,
    "CTCTG": 1823,
    "CTCTT": 1824,
    "CTG--": 1825,
    "CTG-A": 1826,
    "CTG-C": 1827,
    "CTG-G": 1828,
    "CTG-T": 1829,
    "CTGA-": 1830,
    "CTGAA": 1831,
    "CTGAC": 1832,
    "CTGAG": 1833,
    "CTGAT": 1834,
    "CTGC-": 1835,
    "CTGCA": 1836,
    "CTGCC": 1837,
    "CTGCG": 1838,
    "CTGCT": 1839,
    "CTGG-": 1840,
    "CTGGA": 1841,
    "CTGGC": 1842,
    "CTGGG": 1843,
    "CTGGT": 1844,
    "CTGT-": 1845,
    "CTGTA": 1846,
    "CTGTC": 1847,
    "CTGTG": 1848,
    "CTGTT": 1849,
    "CTT--": 1850,
    "CTT-A": 1851,
    "CTT-C": 1852,
    "CTT-G": 1853,
    "CTT-T": 1854,
    "CTTA-": 1855,
    "CTTAA": 1856,
    "CTTAC": 1857,
    "CTTAG": 1858,
    "CTTAT": 1859,
    "CTTC-": 1860,
    "CTTCA": 1861,
    "CTTCC": 1862,
    "CTTCG": 1863,
    "CTTCT": 1864,
    "CTTG-": 1865,
    "CTTGA": 1866,
    "CTTGC": 1867,
    "CTTGG": 1868,
    "CTTGT": 1869,
    "CTTT-": 1870,
    "CTTTA": 1871,
    "CTTTC": 1872,
    "CTTTG": 1873,
    "CTTTT": 1874,
    "G----": 1875,
    "G---A": 1876,
    "G---C": 1877,
    "G---G": 1878,
    "G---T": 1879,
    "G--A-": 1880,
    "G--AA": 1881,
    "G--AC": 1882,
    "G--AG": 1883,
    "G--AT": 1884,
    "G--C-": 1885,
    "G--CA": 1886,
    "G--CC": 1887,
    "G--CG": 1888,
    "G--CT": 1889,
    "G--G-": 1890,
    "G--GA": 1891,
    "G--GC": 1892,
    "G--GG": 1893,
    "G--GT": 1894,
    "G--T-": 1895,
    "G--TA": 1896,
    "G--TC": 1897,
    "G--TG": 1898,
    "G--TT": 1899,
    "G-A--": 1900,
    "G-A-A": 1901,
    "G-A-C": 1902,
    "G-A-G": 1903,
    "G-A-T": 1904,
    "G-AA-": 1905,
    "G-AAA": 1906,
    "G-AAC": 1907,
    "G-AAG": 1908,
    "G-AAT": 1909,
    "G-AC-": 1910,
    "G-ACA": 1911,
    "G-ACC": 1912,
    "G-ACG": 1913,
    "G-ACT": 1914,
    "G-AG-": 1915,
    "G-AGA": 1916,
    "G-AGC": 1917,
    "G-AGG": 1918,
    "G-AGT": 1919,
    "G-AT-": 1920,
    "G-ATA": 1921,
    "G-ATC": 1922,
    "G-ATG": 1923,
    "G-ATT": 1924,
    "G-C--": 1925,
    "G-C-A": 1926,
    "G-C-C": 1927,
    "G-C-G": 1928,
    "G-C-T": 1929,
    "G-CA-": 1930,
    "G-CAA": 1931,
    "G-CAC": 1932,
    "G-CAG": 1933,
    "G-CAT": 1934,
    "G-CC-": 1935,
    "G-CCA": 1936,
    "G-CCC": 1937,
    "G-CCG": 1938,
    "G-CCT": 1939,
    "G-CG-": 1940,
    "G-CGA": 1941,
    "G-CGC": 1942,
    "G-CGG": 1943,
    "G-CGT": 1944,
    "G-CT-": 1945,
    "G-CTA": 1946,
    "G-CTC": 1947,
    "G-CTG": 1948,
    "G-CTT": 1949,
    "G-G--": 1950,
    "G-G-A": 1951,
    "G-G-C": 1952,
    "G-G-G": 1953,
    "G-G-T": 1954,
    "G-GA-": 1955,
    "G-GAA": 1956,
    "G-GAC": 1957,
    "G-GAG": 1958,
    "G-GAT": 1959,
    "G-GC-": 1960,
    "G-GCA": 1961,
    "G-GCC": 1962,
    "G-GCG": 1963,
    "G-GCT": 1964,
    "G-GG-": 1965,
    "G-GGA": 1966,
    "G-GGC": 1967,
    "G-GGG": 1968,
    "G-GGT": 1969,
    "G-GT-": 1970,
    "G-GTA": 1971,
    "G-GTC": 1972,
    "G-GTG": 1973,
    "G-GTT": 1974,
    "G-T--": 1975,
    "G-T-A": 1976,
    "G-T-C": 1977,
    "G-T-G": 1978,
    "G-T-T": 1979,
    "G-TA-": 1980,
    "G-TAA": 1981,
    "G-TAC": 1982,
    "G-TAG": 1983,
    "G-TAT": 1984,
    "G-TC-": 1985,
    "G-TCA": 1986,
    "G-TCC": 1987,
    "G-TCG": 1988,
    "G-TCT": 1989,
    "G-TG-": 1990,
    "G-TGA": 1991,
    "G-TGC": 1992,
    "G-TGG": 1993,
    "G-TGT": 1994,
    "G-TT-": 1995,
    "G-TTA": 1996,
    "G-TTC": 1997,
    "G-TTG": 1998,
    "G-TTT": 1999,
    "GA---": 2000,
    "GA--A": 2001,
    "GA--C": 2002,
    "GA--G": 2003,
    "GA--T": 2004,
    "GA-A-": 2005,
    "GA-AA": 2006,
    "GA-AC": 2007,
    "GA-AG": 2008,
    "GA-AT": 2009,
    "GA-C-": 2010,
    "GA-CA": 2011,
    "GA-CC": 2012,
    "GA-CG": 2013,
    "GA-CT": 2014,
    "GA-G-": 2015,
    "GA-GA": 2016,
    "GA-GC": 2017,
    "GA-GG": 2018,
    "GA-GT": 2019,
    "GA-T-": 2020,
    "GA-TA": 2021,
    "GA-TC": 2022,
    "GA-TG": 2023,
    "GA-TT": 2024,
    "GAA--": 2025,
    "GAA-A": 2026,
    "GAA-C": 2027,
    "GAA-G": 2028,
    "GAA-T": 2029,
    "GAAA-": 2030,
    "GAAAA": 2031,
    "GAAAC": 2032,
    "GAAAG": 2033,
    "GAAAT": 2034,
    "GAAC-": 2035,
    "GAACA": 2036,
    "GAACC": 2037,
    "GAACG": 2038,
    "GAACT": 2039,
    "GAAG-": 2040,
    "GAAGA": 2041,
    "GAAGC": 2042,
    "GAAGG": 2043,
    "GAAGT": 2044,
    "GAAT-": 2045,
    "GAATA": 2046,
    "GAATC": 2047,
    "GAATG": 2048,
    "GAATT": 2049,
    "GAC--": 2050,
    "GAC-A": 2051,
    "GAC-C": 2052,
    "GAC-G": 2053,
    "GAC-T": 2054,
    "GACA-": 2055,
    "GACAA": 2056,
    "GACAC": 2057,
    "GACAG": 2058,
    "GACAT": 2059,
    "GACC-": 2060,
    "GACCA": 2061,
    "GACCC": 2062,
    "GACCG": 2063,
    "GACCT": 2064,
    "GACG-": 2065,
    "GACGA": 2066,
    "GACGC": 2067,
    "GACGG": 2068,
    "GACGT": 2069,
    "GACT-": 2070,
    "GACTA": 2071,
    "GACTC": 2072,
    "GACTG": 2073,
    "GACTT": 2074,
    "GAG--": 2075,
    "GAG-A": 2076,
    "GAG-C": 2077,
    "GAG-G": 2078,
    "GAG-T": 2079,
    "GAGA-": 2080,
    "GAGAA": 2081,
    "GAGAC": 2082,
    "GAGAG": 2083,
    "GAGAT": 2084,
    "GAGC-": 2085,
    "GAGCA": 2086,
    "GAGCC": 2087,
    "GAGCG": 2088,
    "GAGCT": 2089,
    "GAGG-": 2090,
    "GAGGA": 2091,
    "GAGGC": 2092,
    "GAGGG": 2093,
    "GAGGT": 2094,
    "GAGT-": 2095,
    "GAGTA": 2096,
    "GAGTC": 2097,
    "GAGTG": 2098,
    "GAGTT": 2099,
    "GAT--": 2100,
    "GAT-A": 2101,
    "GAT-C": 2102,
    "GAT-G": 2103,
    "GAT-T": 2104,
    "GATA-": 2105,
    "GATAA": 2106,
    "GATAC": 2107,
    "GATAG": 2108,
    "GATAT": 2109,
    "GATC-": 2110,
    "GATCA": 2111,
    "GATCC": 2112,
    "GATCG": 2113,
    "GATCT": 2114,
    "GATG-": 2115,
    "GATGA": 2116,
    "GATGC": 2117,
    "GATGG": 2118,
    "GATGT": 2119,
    "GATT-": 2120,
    "GATTA": 2121,
    "GATTC": 2122,
    "GATTG": 2123,
    "GATTT": 2124,
    "GC---": 2125,
    "GC--A": 2126,
    "GC--C": 2127,
    "GC--G": 2128,
    "GC--T": 2129,
    "GC-A-": 2130,
    "GC-AA": 2131,
    "GC-AC": 2132,
    "GC-AG": 2133,
    "GC-AT": 2134,
    "GC-C-": 2135,
    "GC-CA": 2136,
    "GC-CC": 2137,
    "GC-CG": 2138,
    "GC-CT": 2139,
    "GC-G-": 2140,
    "GC-GA": 2141,
    "GC-GC": 2142,
    "GC-GG": 2143,
    "GC-GT": 2144,
    "GC-T-": 2145,
    "GC-TA": 2146,
    "GC-TC": 2147,
    "GC-TG": 2148,
    "GC-TT": 2149,
    "GCA--": 2150,
    "GCA-A": 2151,
    "GCA-C": 2152,
    "GCA-G": 2153,
    "GCA-T": 2154,
    "GCAA-": 2155,
    "GCAAA": 2156,
    "GCAAC": 2157,
    "GCAAG": 2158,
    "GCAAT": 2159,
    "GCAC-": 2160,
    "GCACA": 2161,
    "GCACC": 2162,
    "GCACG": 2163,
    "GCACT": 2164,
    "GCAG-": 2165,
    "GCAGA": 2166,
    "GCAGC": 2167,
    "GCAGG": 2168,
    "GCAGT": 2169,
    "GCAT-": 2170,
    "GCATA": 2171,
    "GCATC": 2172,
    "GCATG": 2173,
    "GCATT": 2174,
    "GCC--": 2175,
    "GCC-A": 2176,
    "GCC-C": 2177,
    "GCC-G": 2178,
    "GCC-T": 2179,
    "GCCA-": 2180,
    "GCCAA": 2181,
    "GCCAC": 2182,
    "GCCAG": 2183,
    "GCCAT": 2184,
    "GCCC-": 2185,
    "GCCCA": 2186,
    "GCCCC": 2187,
    "GCCCG": 2188,
    "GCCCT": 2189,
    "GCCG-": 2190,
    "GCCGA": 2191,
    "GCCGC": 2192,
    "GCCGG": 2193,
    "GCCGT": 2194,
    "GCCT-": 2195,
    "GCCTA": 2196,
    "GCCTC": 2197,
    "GCCTG": 2198,
    "GCCTT": 2199,
    "GCG--": 2200,
    "GCG-A": 2201,
    "GCG-C": 2202,
    "GCG-G": 2203,
    "GCG-T": 2204,
    "GCGA-": 2205,
    "GCGAA": 2206,
    "GCGAC": 2207,
    "GCGAG": 2208,
    "GCGAT": 2209,
    "GCGC-": 2210,
    "GCGCA": 2211,
    "GCGCC": 2212,
    "GCGCG": 2213,
    "GCGCT": 2214,
    "GCGG-": 2215,
    "GCGGA": 2216,
    "GCGGC": 2217,
    "GCGGG": 2218,
    "GCGGT": 2219,
    "GCGT-": 2220,
    "GCGTA": 2221,
    "GCGTC": 2222,
    "GCGTG": 2223,
    "GCGTT": 2224,
    "GCT--": 2225,
    "GCT-A": 2226,
    "GCT-C": 2227,
    "GCT-G": 2228,
    "GCT-T": 2229,
    "GCTA-": 2230,
    "GCTAA": 2231,
    "GCTAC": 2232,
    "GCTAG": 2233,
    "GCTAT": 2234,
    "GCTC-": 2235,
    "GCTCA": 2236,
    "GCTCC": 2237,
    "GCTCG": 2238,
    "GCTCT": 2239,
    "GCTG-": 2240,
    "GCTGA": 2241,
    "GCTGC": 2242,
    "GCTGG": 2243,
    "GCTGT": 2244,
    "GCTT-": 2245,
    "GCTTA": 2246,
    "GCTTC": 2247,
    "GCTTG": 2248,
    "GCTTT": 2249,
    "GG---": 2250,
    "GG--A": 2251,
    "GG--C": 2252,
    "GG--G": 2253,
    "GG--T": 2254,
    "GG-A-": 2255,
    "GG-AA": 2256,
    "GG-AC": 2257,
    "GG-AG": 2258,
    "GG-AT": 2259,
    "GG-C-": 2260,
    "GG-CA": 2261,
    "GG-CC": 2262,
    "GG-CG": 2263,
    "GG-CT": 2264,
    "GG-G-": 2265,
    "GG-GA": 2266,
    "GG-GC": 2267,
    "GG-GG": 2268,
    "GG-GT": 2269,
    "GG-T-": 2270,
    "GG-TA": 2271,
    "GG-TC": 2272,
    "GG-TG": 2273,
    "GG-TT": 2274,
    "GGA--": 2275,
    "GGA-A": 2276,
    "GGA-C": 2277,
    "GGA-G": 2278,
    "GGA-T": 2279,
    "GGAA-": 2280,
    "GGAAA": 2281,
    "GGAAC": 2282,
    "GGAAG": 2283,
    "GGAAT": 2284,
    "GGAC-": 2285,
    "GGACA": 2286,
    "GGACC": 2287,
    "GGACG": 2288,
    "GGACT": 2289,
    "GGAG-": 2290,
    "GGAGA": 2291,
    "GGAGC": 2292,
    "GGAGG": 2293,
    "GGAGT": 2294,
    "GGAT-": 2295,
    "GGATA": 2296,
    "GGATC": 2297,
    "GGATG": 2298,
    "GGATT": 2299,
    "GGC--": 2300,
    "GGC-A": 2301,
    "GGC-C": 2302,
    "GGC-G": 2303,
    "GGC-T": 2304,
    "GGCA-": 2305,
    "GGCAA": 2306,
    "GGCAC": 2307,
    "GGCAG": 2308,
    "GGCAT": 2309,
    "GGCC-": 2310,
    "GGCCA": 2311,
    "GGCCC": 2312,
    "GGCCG": 2313,
    "GGCCT": 2314,
    "GGCG-": 2315,
    "GGCGA": 2316,
    "GGCGC": 2317,
    "GGCGG": 2318,
    "GGCGT": 2319,
    "GGCT-": 2320,
    "GGCTA": 2321,
    "GGCTC": 2322,
    "GGCTG": 2323,
    "GGCTT": 2324,
    "GGG--": 2325,
    "GGG-A": 2326,
    "GGG-C": 2327,
    "GGG-G": 2328,
    "GGG-T": 2329,
    "GGGA-": 2330,
    "GGGAA": 2331,
    "GGGAC": 2332,
    "GGGAG": 2333,
    "GGGAT": 2334,
    "GGGC-": 2335,
    "GGGCA": 2336,
    "GGGCC": 2337,
    "GGGCG": 2338,
    "GGGCT": 2339,
    "GGGG-": 2340,
    "GGGGA": 2341,
    "GGGGC": 2342,
    "GGGGG": 2343,
    "GGGGT": 2344,
    "GGGT-": 2345,
    "GGGTA": 2346,
    "GGGTC": 2347,
    "GGGTG": 2348,
    "GGGTT": 2349,
    "GGT--": 2350,
    "GGT-A": 2351,
    "GGT-C": 2352,
    "GGT-G": 2353,
    "GGT-T": 2354,
    "GGTA-": 2355,
    "GGTAA": 2356,
    "GGTAC": 2357,
    "GGTAG": 2358,
    "GGTAT": 2359,
    "GGTC-": 2360,
    "GGTCA": 2361,
    "GGTCC": 2362,
    "GGTCG": 2363,
    "GGTCT": 2364,
    "GGTG-": 2365,
    "GGTGA": 2366,
    "GGTGC": 2367,
    "GGTGG": 2368,
    "GGTGT": 2369,
    "GGTT-": 2370,
    "GGTTA": 2371,
    "GGTTC": 2372,
    "GGTTG": 2373,
    "GGTTT": 2374,
    "GT---": 2375,
    "GT--A": 2376,
    "GT--C": 2377,
    "GT--G": 2378,
    "GT--T": 2379,
    "GT-A-": 2380,
    "GT-AA": 2381,
    "GT-AC": 2382,
    "GT-AG": 2383,
    "GT-AT": 2384,
    "GT-C-": 2385,
    "GT-CA": 2386,
    "GT-CC": 2387,
    "GT-CG": 2388,
    "GT-CT": 2389,
    "GT-G-": 2390,
    "GT-GA": 2391,
    "GT-GC": 2392,
    "GT-GG": 2393,
    "GT-GT": 2394,
    "GT-T-": 2395,
    "GT-TA": 2396,
    "GT-TC": 2397,
    "GT-TG": 2398,
    "GT-TT": 2399,
    "GTA--": 2400,
    "GTA-A": 2401,
    "GTA-C": 2402,
    "GTA-G": 2403,
    "GTA-T": 2404,
    "GTAA-": 2405,
    "GTAAA": 2406,
    "GTAAC": 2407,
    "GTAAG": 2408,
    "GTAAT": 2409,
    "GTAC-": 2410,
    "GTACA": 2411,
    "GTACC": 2412,
    "GTACG": 2413,
    "GTACT": 2414,
    "GTAG-": 2415,
    "GTAGA": 2416,
    "GTAGC": 2417,
    "GTAGG": 2418,
    "GTAGT": 2419,
    "GTAT-": 2420,
    "GTATA": 2421,
    "GTATC": 2422,
    "GTATG": 2423,
    "GTATT": 2424,
    "GTC--": 2425,
    "GTC-A": 2426,
    "GTC-C": 2427,
    "GTC-G": 2428,
    "GTC-T": 2429,
    "GTCA-": 2430,
    "GTCAA": 2431,
    "GTCAC": 2432,
    "GTCAG": 2433,
    "GTCAT": 2434,
    "GTCC-": 2435,
    "GTCCA": 2436,
    "GTCCC": 2437,
    "GTCCG": 2438,
    "GTCCT": 2439,
    "GTCG-": 2440,
    "GTCGA": 2441,
    "GTCGC": 2442,
    "GTCGG": 2443,
    "GTCGT": 2444,
    "GTCT-": 2445,
    "GTCTA": 2446,
    "GTCTC": 2447,
    "GTCTG": 2448,
    "GTCTT": 2449,
    "GTG--": 2450,
    "GTG-A": 2451,
    "GTG-C": 2452,
    "GTG-G": 2453,
    "GTG-T": 2454,
    "GTGA-": 2455,
    "GTGAA": 2456,
    "GTGAC": 2457,
    "GTGAG": 2458,
    "GTGAT": 2459,
    "GTGC-": 2460,
    "GTGCA": 2461,
    "GTGCC": 2462,
    "GTGCG": 2463,
    "GTGCT": 2464,
    "GTGG-": 2465,
    "GTGGA": 2466,
    "GTGGC": 2467,
    "GTGGG": 2468,
    "GTGGT": 2469,
    "GTGT-": 2470,
    "GTGTA": 2471,
    "GTGTC": 2472,
    "GTGTG": 2473,
    "GTGTT": 2474,
    "GTT--": 2475,
    "GTT-A": 2476,
    "GTT-C": 2477,
    "GTT-G": 2478,
    "GTT-T": 2479,
    "GTTA-": 2480,
    "GTTAA": 2481,
    "GTTAC": 2482,
    "GTTAG": 2483,
    "GTTAT": 2484,
    "GTTC-": 2485,
    "GTTCA": 2486,
    "GTTCC": 2487,
    "GTTCG": 2488,
    "GTTCT": 2489,
    "GTTG-": 2490,
    "GTTGA": 2491,
    "GTTGC": 2492,
    "GTTGG": 2493,
    "GTTGT": 2494,
    "GTTT-": 2495,
    "GTTTA": 2496,
    "GTTTC": 2497,
    "GTTTG": 2498,
    "GTTTT": 2499,
    "T----": 2500,
    "T---A": 2501,
    "T---C": 2502,
    "T---G": 2503,
    "T---T": 2504,
    "T--A-": 2505,
    "T--AA": 2506,
    "T--AC": 2507,
    "T--AG": 2508,
    "T--AT": 2509,
    "T--C-": 2510,
    "T--CA": 2511,
    "T--CC": 2512,
    "T--CG": 2513,
    "T--CT": 2514,
    "T--G-": 2515,
    "T--GA": 2516,
    "T--GC": 2517,
    "T--GG": 2518,
    "T--GT": 2519,
    "T--T-": 2520,
    "T--TA": 2521,
    "T--TC": 2522,
    "T--TG": 2523,
    "T--TT": 2524,
    "T-A--": 2525,
    "T-A-A": 2526,
    "T-A-C": 2527,
    "T-A-G": 2528,
    "T-A-T": 2529,
    "T-AA-": 2530,
    "T-AAA": 2531,
    "T-AAC": 2532,
    "T-AAG": 2533,
    "T-AAT": 2534,
    "T-AC-": 2535,
    "T-ACA": 2536,
    "T-ACC": 2537,
    "T-ACG": 2538,
    "T-ACT": 2539,
    "T-AG-": 2540,
    "T-AGA": 2541,
    "T-AGC": 2542,
    "T-AGG": 2543,
    "T-AGT": 2544,
    "T-AT-": 2545,
    "T-ATA": 2546,
    "T-ATC": 2547,
    "T-ATG": 2548,
    "T-ATT": 2549,
    "T-C--": 2550,
    "T-C-A": 2551,
    "T-C-C": 2552,
    "T-C-G": 2553,
    "T-C-T": 2554,
    "T-CA-": 2555,
    "T-CAA": 2556,
    "T-CAC": 2557,
    "T-CAG": 2558,
    "T-CAT": 2559,
    "T-CC-": 2560,
    "T-CCA": 2561,
    "T-CCC": 2562,
    "T-CCG": 2563,
    "T-CCT": 2564,
    "T-CG-": 2565,
    "T-CGA": 2566,
    "T-CGC": 2567,
    "T-CGG": 2568,
    "T-CGT": 2569,
    "T-CT-": 2570,
    "T-CTA": 2571,
    "T-CTC": 2572,
    "T-CTG": 2573,
    "T-CTT": 2574,
    "T-G--": 2575,
    "T-G-A": 2576,
    "T-G-C": 2577,
    "T-G-G": 2578,
    "T-G-T": 2579,
    "T-GA-": 2580,
    "T-GAA": 2581,
    "T-GAC": 2582,
    "T-GAG": 2583,
    "T-GAT": 2584,
    "T-GC-": 2585,
    "T-GCA": 2586,
    "T-GCC": 2587,
    "T-GCG": 2588,
    "T-GCT": 2589,
    "T-GG-": 2590,
    "T-GGA": 2591,
    "T-GGC": 2592,
    "T-GGG": 2593,
    "T-GGT": 2594,
    "T-GT-": 2595,
    "T-GTA": 2596,
    "T-GTC": 2597,
    "T-GTG": 2598,
    "T-GTT": 2599,
    "T-T--": 2600,
    "T-T-A": 2601,
    "T-T-C": 2602,
    "T-T-G": 2603,
    "T-T-T": 2604,
    "T-TA-": 2605,
    "T-TAA": 2606,
    "T-TAC": 2607,
    "T-TAG": 2608,
    "T-TAT": 2609,
    "T-TC-": 2610,
    "T-TCA": 2611,
    "T-TCC": 2612,
    "T-TCG": 2613,
    "T-TCT": 2614,
    "T-TG-": 2615,
    "T-TGA": 2616,
    "T-TGC": 2617,
    "T-TGG": 2618,
    "T-TGT": 2619,
    "T-TT-": 2620,
    "T-TTA": 2621,
    "T-TTC": 2622,
    "T-TTG": 2623,
    "T-TTT": 2624,
    "TA---": 2625,
    "TA--A": 2626,
    "TA--C": 2627,
    "TA--G": 2628,
    "TA--T": 2629,
    "TA-A-": 2630,
    "TA-AA": 2631,
    "TA-AC": 2632,
    "TA-AG": 2633,
    "TA-AT": 2634,
    "TA-C-": 2635,
    "TA-CA": 2636,
    "TA-CC": 2637,
    "TA-CG": 2638,
    "TA-CT": 2639,
    "TA-G-": 2640,
    "TA-GA": 2641,
    "TA-GC": 2642,
    "TA-GG": 2643,
    "TA-GT": 2644,
    "TA-T-": 2645,
    "TA-TA": 2646,
    "TA-TC": 2647,
    "TA-TG": 2648,
    "TA-TT": 2649,
    "TAA--": 2650,
    "TAA-A": 2651,
    "TAA-C": 2652,
    "TAA-G": 2653,
    "TAA-T": 2654,
    "TAAA-": 2655,
    "TAAAA": 2656,
    "TAAAC": 2657,
    "TAAAG": 2658,
    "TAAAT": 2659,
    "TAAC-": 2660,
    "TAACA": 2661,
    "TAACC": 2662,
    "TAACG": 2663,
    "TAACT": 2664,
    "TAAG-": 2665,
    "TAAGA": 2666,
    "TAAGC": 2667,
    "TAAGG": 2668,
    "TAAGT": 2669,
    "TAAT-": 2670,
    "TAATA": 2671,
    "TAATC": 2672,
    "TAATG": 2673,
    "TAATT": 2674,
    "TAC--": 2675,
    "TAC-A": 2676,
    "TAC-C": 2677,
    "TAC-G": 2678,
    "TAC-T": 2679,
    "TACA-": 2680,
    "TACAA": 2681,
    "TACAC": 2682,
    "TACAG": 2683,
    "TACAT": 2684,
    "TACC-": 2685,
    "TACCA": 2686,
    "TACCC": 2687,
    "TACCG": 2688,
    "TACCT": 2689,
    "TACG-": 2690,
    "TACGA": 2691,
    "TACGC": 2692,
    "TACGG": 2693,
    "TACGT": 2694,
    "TACT-": 2695,
    "TACTA": 2696,
    "TACTC": 2697,
    "TACTG": 2698,
    "TACTT": 2699,
    "TAG--": 2700,
    "TAG-A": 2701,
    "TAG-C": 2702,
    "TAG-G": 2703,
    "TAG-T": 2704,
    "TAGA-": 2705,
    "TAGAA": 2706,
    "TAGAC": 2707,
    "TAGAG": 2708,
    "TAGAT": 2709,
    "TAGC-": 2710,
    "TAGCA": 2711,
    "TAGCC": 2712,
    "TAGCG": 2713,
    "TAGCT": 2714,
    "TAGG-": 2715,
    "TAGGA": 2716,
    "TAGGC": 2717,
    "TAGGG": 2718,
    "TAGGT": 2719,
    "TAGT-": 2720,
    "TAGTA": 2721,
    "TAGTC": 2722,
    "TAGTG": 2723,
    "TAGTT": 2724,
    "TAT--": 2725,
    "TAT-A": 2726,
    "TAT-C": 2727,
    "TAT-G": 2728,
    "TAT-T": 2729,
    "TATA-": 2730,
    "TATAA": 2731,
    "TATAC": 2732,
    "TATAG": 2733,
    "TATAT": 2734,
    "TATC-": 2735,
    "TATCA": 2736,
    "TATCC": 2737,
    "TATCG": 2738,
    "TATCT": 2739,
    "TATG-": 2740,
    "TATGA": 2741,
    "TATGC": 2742,
    "TATGG": 2743,
    "TATGT": 2744,
    "TATT-": 2745,
    "TATTA": 2746,
    "TATTC": 2747,
    "TATTG": 2748,
    "TATTT": 2749,
    "TC---": 2750,
    "TC--A": 2751,
    "TC--C": 2752,
    "TC--G": 2753,
    "TC--T": 2754,
    "TC-A-": 2755,
    "TC-AA": 2756,
    "TC-AC": 2757,
    "TC-AG": 2758,
    "TC-AT": 2759,
    "TC-C-": 2760,
    "TC-CA": 2761,
    "TC-CC": 2762,
    "TC-CG": 2763,
    "TC-CT": 2764,
    "TC-G-": 2765,
    "TC-GA": 2766,
    "TC-GC": 2767,
    "TC-GG": 2768,
    "TC-GT": 2769,
    "TC-T-": 2770,
    "TC-TA": 2771,
    "TC-TC": 2772,
    "TC-TG": 2773,
    "TC-TT": 2774,
    "TCA--": 2775,
    "TCA-A": 2776,
    "TCA-C": 2777,
    "TCA-G": 2778,
    "TCA-T": 2779,
    "TCAA-": 2780,
    "TCAAA": 2781,
    "TCAAC": 2782,
    "TCAAG": 2783,
    "TCAAT": 2784,
    "TCAC-": 2785,
    "TCACA": 2786,
    "TCACC": 2787,
    "TCACG": 2788,
    "TCACT": 2789,
    "TCAG-": 2790,
    "TCAGA": 2791,
    "TCAGC": 2792,
    "TCAGG": 2793,
    "TCAGT": 2794,
    "TCAT-": 2795,
    "TCATA": 2796,
    "TCATC": 2797,
    "TCATG": 2798,
    "TCATT": 2799,
    "TCC--": 2800,
    "TCC-A": 2801,
    "TCC-C": 2802,
    "TCC-G": 2803,
    "TCC-T": 2804,
    "TCCA-": 2805,
    "TCCAA": 2806,
    "TCCAC": 2807,
    "TCCAG": 2808,
    "TCCAT": 2809,
    "TCCC-": 2810,
    "TCCCA": 2811,
    "TCCCC": 2812,
    "TCCCG": 2813,
    "TCCCT": 2814,
    "TCCG-": 2815,
    "TCCGA": 2816,
    "TCCGC": 2817,
    "TCCGG": 2818,
    "TCCGT": 2819,
    "TCCT-": 2820,
    "TCCTA": 2821,
    "TCCTC": 2822,
    "TCCTG": 2823,
    "TCCTT": 2824,
    "TCG--": 2825,
    "TCG-A": 2826,
    "TCG-C": 2827,
    "TCG-G": 2828,
    "TCG-T": 2829,
    "TCGA-": 2830,
    "TCGAA": 2831,
    "TCGAC": 2832,
    "TCGAG": 2833,
    "TCGAT": 2834,
    "TCGC-": 2835,
    "TCGCA": 2836,
    "TCGCC": 2837,
    "TCGCG": 2838,
    "TCGCT": 2839,
    "TCGG-": 2840,
    "TCGGA": 2841,
    "TCGGC": 2842,
    "TCGGG": 2843,
    "TCGGT": 2844,
    "TCGT-": 2845,
    "TCGTA": 2846,
    "TCGTC": 2847,
    "TCGTG": 2848,
    "TCGTT": 2849,
    "TCT--": 2850,
    "TCT-A": 2851,
    "TCT-C": 2852,
    "TCT-G": 2853,
    "TCT-T": 2854,
    "TCTA-": 2855,
    "TCTAA": 2856,
    "TCTAC": 2857,
    "TCTAG": 2858,
    "TCTAT": 2859,
    "TCTC-": 2860,
    "TCTCA": 2861,
    "TCTCC": 2862,
    "TCTCG": 2863,
    "TCTCT": 2864,
    "TCTG-": 2865,
    "TCTGA": 2866,
    "TCTGC": 2867,
    "TCTGG": 2868,
    "TCTGT": 2869,
    "TCTT-": 2870,
    "TCTTA": 2871,
    "TCTTC": 2872,
    "TCTTG": 2873,
    "TCTTT": 2874,
    "TG---": 2875,
    "TG--A": 2876,
    "TG--C": 2877,
    "TG--G": 2878,
    "TG--T": 2879,
    "TG-A-": 2880,
    "TG-AA": 2881,
    "TG-AC": 2882,
    "TG-AG": 2883,
    "TG-AT": 2884,
    "TG-C-": 2885,
    "TG-CA": 2886,
    "TG-CC": 2887,
    "TG-CG": 2888,
    "TG-CT": 2889,
    "TG-G-": 2890,
    "TG-GA": 2891,
    "TG-GC": 2892,
    "TG-GG": 2893,
    "TG-GT": 2894,
    "TG-T-": 2895,
    "TG-TA": 2896,
    "TG-TC": 2897,
    "TG-TG": 2898,
    "TG-TT": 2899,
    "TGA--": 2900,
    "TGA-A": 2901,
    "TGA-C": 2902,
    "TGA-G": 2903,
    "TGA-T": 2904,
    "TGAA-": 2905,
    "TGAAA": 2906,
    "TGAAC": 2907,
    "TGAAG": 2908,
    "TGAAT": 2909,
    "TGAC-": 2910,
    "TGACA": 2911,
    "TGACC": 2912,
    "TGACG": 2913,
    "TGACT": 2914,
    "TGAG-": 2915,
    "TGAGA": 2916,
    "TGAGC": 2917,
    "TGAGG": 2918,
    "TGAGT": 2919,
    "TGAT-": 2920,
    "TGATA": 2921,
    "TGATC": 2922,
    "TGATG": 2923,
    "TGATT": 2924,
    "TGC--": 2925,
    "TGC-A": 2926,
    "TGC-C": 2927,
    "TGC-G": 2928,
    "TGC-T": 2929,
    "TGCA-": 2930,
    "TGCAA": 2931,
    "TGCAC": 2932,
    "TGCAG": 2933,
    "TGCAT": 2934,
    "TGCC-": 2935,
    "TGCCA": 2936,
    "TGCCC": 2937,
    "TGCCG": 2938,
    "TGCCT": 2939,
    "TGCG-": 2940,
    "TGCGA": 2941,
    "TGCGC": 2942,
    "TGCGG": 2943,
    "TGCGT": 2944,
    "TGCT-": 2945,
    "TGCTA": 2946,
    "TGCTC": 2947,
    "TGCTG": 2948,
    "TGCTT": 2949,
    "TGG--": 2950,
    "TGG-A": 2951,
    "TGG-C": 2952,
    "TGG-G": 2953,
    "TGG-T": 2954,
    "TGGA-": 2955,
    "TGGAA": 2956,
    "TGGAC": 2957,
    "TGGAG": 2958,
    "TGGAT": 2959,
    "TGGC-": 2960,
    "TGGCA": 2961,
    "TGGCC": 2962,
    "TGGCG": 2963,
    "TGGCT": 2964,
    "TGGG-": 2965,
    "TGGGA": 2966,
    "TGGGC": 2967,
    "TGGGG": 2968,
    "TGGGT": 2969,
    "TGGT-": 2970,
    "TGGTA": 2971,
    "TGGTC": 2972,
    "TGGTG": 2973,
    "TGGTT": 2974,
    "TGT--": 2975,
    "TGT-A": 2976,
    "TGT-C": 2977,
    "TGT-G": 2978,
    "TGT-T": 2979,
    "TGTA-": 2980,
    "TGTAA": 2981,
    "TGTAC": 2982,
    "TGTAG": 2983,
    "TGTAT": 2984,
    "TGTC-": 2985,
    "TGTCA": 2986,
    "TGTCC": 2987,
    "TGTCG": 2988,
    "TGTCT": 2989,
    "TGTG-": 2990,
    "TGTGA": 2991,
    "TGTGC": 2992,
    "TGTGG": 2993,
    "TGTGT": 2994,
    "TGTT-": 2995,
    "TGTTA": 2996,
    "TGTTC": 2997,
    "TGTTG": 2998,
    "TGTTT": 2999,
    "TT---": 3000,
    "TT--A": 3001,
    "TT--C": 3002,
    "TT--G": 3003,
    "TT--T": 3004,
    "TT-A-": 3005,
    "TT-AA": 3006,
    "TT-AC": 3007,
    "TT-AG": 3008,
    "TT-AT": 3009,
    "TT-C-": 3010,
    "TT-CA": 3011,
    "TT-CC": 3012,
    "TT-CG": 3013,
    "TT-CT": 3014,
    "TT-G-": 3015,
    "TT-GA": 3016,
    "TT-GC": 3017,
    "TT-GG": 3018,
    "TT-GT": 3019,
    "TT-T-": 3020,
    "TT-TA": 3021,
    "TT-TC": 3022,
    "TT-TG": 3023,
    "TT-TT": 3024,
    "TTA--": 3025,
    "TTA-A": 3026,
    "TTA-C": 3027,
    "TTA-G": 3028,
    "TTA-T": 3029,
    "TTAA-": 3030,
    "TTAAA": 3031,
    "TTAAC": 3032,
    "TTAAG": 3033,
    "TTAAT": 3034,
    "TTAC-": 3035,
    "TTACA": 3036,
    "TTACC": 3037,
    "TTACG": 3038,
    "TTACT": 3039,
    "TTAG-": 3040,
    "TTAGA": 3041,
    "TTAGC": 3042,
    "TTAGG": 3043,
    "TTAGT": 3044,
    "TTAT-": 3045,
    "TTATA": 3046,
    "TTATC": 3047,
    "TTATG": 3048,
    "TTATT": 3049,
    "TTC--": 3050,
    "TTC-A": 3051,
    "TTC-C": 3052,
    "TTC-G": 3053,
    "TTC-T": 3054,
    "TTCA-": 3055,
    "TTCAA": 3056,
    "TTCAC": 3057,
    "TTCAG": 3058,
    "TTCAT": 3059,
    "TTCC-": 3060,
    "TTCCA": 3061,
    "TTCCC": 3062,
    "TTCCG": 3063,
    "TTCCT": 3064,
    "TTCG-": 3065,
    "TTCGA": 3066,
    "TTCGC": 3067,
    "TTCGG": 3068,
    "TTCGT": 3069,
    "TTCT-": 3070,
    "TTCTA": 3071,
    "TTCTC": 3072,
    "TTCTG": 3073,
    "TTCTT": 3074,
    "TTG--": 3075,
    "TTG-A": 3076,
    "TTG-C": 3077,
    "TTG-G": 3078,
    "TTG-T": 3079,
    "TTGA-": 3080,
    "TTGAA": 3081,
    "TTGAC": 3082,
    "TTGAG": 3083,
    "TTGAT": 3084,
    "TTGC-": 3085,
    "TTGCA": 3086,
    "TTGCC": 3087,
    "TTGCG": 3088,
    "TTGCT": 3089,
    "TTGG-": 3090,
    "TTGGA": 3091,
    "TTGGC": 3092,
    "TTGGG": 3093,
    "TTGGT": 3094,
    "TTGT-": 3095,
    "TTGTA": 3096,
    "TTGTC": 3097,
    "TTGTG": 3098,
    "TTGTT": 3099,
    "TTT--": 3100,
    "TTT-A": 3101,
    "TTT-C": 3102,
    "TTT-G": 3103,
    "TTT-T": 3104,
    "TTTA-": 3105,
    "TTTAA": 3106,
    "TTTAC": 3107,
    "TTTAG": 3108,
    "TTTAT": 3109,
    "TTTC-": 3110,
    "TTTCA": 3111,
    "TTTCC": 3112,
    "TTTCG": 3113,
    "TTTCT": 3114,
    "TTTG-": 3115,
    "TTTGA": 3116,
    "TTTGC": 3117,
    "TTTGG": 3118,
    "TTTGT": 3119,
    "TTTT-": 3120,
    "TTTTA": 3121,
    "TTTTC": 3122,
    "TTTTG": 3123,
    "TTTTT": 3124
  }
}